{
  "files": [ "..\\..\\rpmalloc\\rpmalloc\\rpmalloc.c" ],
  "outpath": ".",
  "language":  "oxygene",
  "namespace": "RemObjects.Elements.System.rpmalloc",
  "defines": [
    "size_t=IntPtr",
    "uintptr_t=UIntPtr",
    "ptrdiff_t=IntPtr",
    "int64_t=Int64",
    "uint64_t=UInt64",
    "int32_t=Int32",
    "uint32_t=UInt32",
    "int16_t=Int16",
    "uint16_t=UInt16",
    "int8_t=Byte",
    "uint8_t=SByte",
    "EINVAL=22",
    "ENOMEM=12",
    "DISABLE_UNMAP=1",
    "ENABLE_UNLIMITED_CACHE=0",
    "ENABLE_GLOBAL_CACHE"
  ],
  "uses":  ["rtl"],
  "nonDefines": [
    "ENABLE_ASSERTS",
    "PLATFORM_WINDOWS",
    "PLATFORM_POSIX",
    "ARCH_64BIT",
    "ENABLE_STATISTICS",
    "ENABLE_UNLIMITED_THREAD_CACHE",
    "ENABLE_UNLIMITED_GLOBAL_CACHE"
  ],
  "includes": {
    "stdio.h":"",
    "stdlib.h":"",
    "stdatomic.h":"",
    "stddef.h": "",
    "stdint.h": "",
    "string.h": "",
    "assert.h": "",
    "errno.h": "",
    "unistd.h": "",
    "pthread.h": "",
    "sys/mman.h": "",
    "sched.h": ""
  },
  "includePaths": ["..\\..\\rpmalloc\\rpmalloc\\" ]
}